ysyfinance/None.py
ysyfinance/__init__.py
ysyfinance/_nbdev.py
ysyfinance/bootstrap.py
ysyfinance/commons.py
ysyfinance/config.py
ysyfinance/adapters/__init__.py
ysyfinance/adapters/cache.py
ysyfinance/adapters/repository.py
ysyfinance/budget/__init__.py
ysyfinance/budget/core.py
ysyfinance/budget/domain.py
ysyfinance/domain/__init__.py
ysyfinance/domain/commands.py
ysyfinance/domain/events.py
ysyfinance/domain/model.py
ysyfinance/domain/tools.py
ysyfinance/entrypoints/__init__.py
ysyfinance/entrypoints/flask_app.py
ysyfinance/entrypoints/functions.py
ysyfinance/service_layer/__init__.py
ysyfinance/service_layer/handlers.py
ysyfinance/service_layer/messagebus.py
ysyfinance/service_layer/unit_of_work.py
ysyfinance/service_layer/views.py
ysyfinance-0.0.3.dist-info/LICENSE
ysyfinance-0.0.3.dist-info/METADATA
ysyfinance-0.0.3.dist-info/WHEEL
ysyfinance-0.0.3.dist-info/entry_points.txt
ysyfinance-0.0.3.dist-info/top_level.txt
ysyfinance-0.0.3.dist-info/RECORD
